psql2csv/__init__.py
psql2csv/cli.py
psql2csv/database.py
psql2csv/download.py
psql2csv-1.1.4.dist-info/DESCRIPTION.rst
psql2csv-1.1.4.dist-info/METADATA
psql2csv-1.1.4.dist-info/RECORD
psql2csv-1.1.4.dist-info/WHEEL
psql2csv-1.1.4.dist-info/entry_points.txt
psql2csv-1.1.4.dist-info/metadata.json
psql2csv-1.1.4.dist-info/top_level.txt
