Metadata-Version: 2.0
Name: psql2csv
Version: 1.1.4
Summary: A library and a CLI to download PostgreSQL schemas and tables
Home-page: http://www.joeyism.com
Author: Joey Sham
Author-email: sham.joey@gmail.com
License: UNKNOWN
Download-URL: https://github.com/joeyism/linkedin_scraper/dist/1.1.4.tar.gz
Platform: UNKNOWN
Requires-Dist: nprint
Requires-Dist: click
Requires-Dist: psycopg2
